LICENSE
README.md
setup.cfg
setup.py
src/database_version_control.egg-info/PKG-INFO
src/database_version_control.egg-info/SOURCES.txt
src/database_version_control.egg-info/dependency_links.txt
src/database_version_control.egg-info/entry_points.txt
src/database_version_control.egg-info/requires.txt
src/database_version_control.egg-info/top_level.txt
src/dvc/__init__.py
src/dvc/version.py
src/dvc/app/__init__.py
src/dvc/app/cli/__init__.py
src/dvc/app/cli/main.py
src/dvc/app/cli/commands/__init__.py
src/dvc/app/cli/commands/config.py
src/dvc/app/cli/commands/database/__init__.py
src/dvc/app/cli/commands/database/backend.py
src/dvc/core/__init__.py
src/dvc/core/config.py
src/dvc/core/exception.py
src/dvc/core/file.py
src/dvc/core/hash.py
src/dvc/core/logger.py
src/dvc/core/regex.py
src/dvc/core/struct.py
src/dvc/core/database/__init__.py
src/dvc/core/database/bigquery/__init__.py
src/dvc/core/database/mysql/__init__.py
src/dvc/core/database/postgres/__init__.py
src/dvc/core/database/postgres/scm_dvc__create_scm_and_tbls.sql
src/dvc/core/database/postgres/scm_dvc__insert_tbl_database_revision_history.sql
src/dvc/core/database/postgres/scm_dvc__select_latest_database_version.sql