Metadata-Version: 2.1
Name: database-version-control
Version: 0.5.1
Summary: Version control your database!
Home-page: https://github.com/kenho811/Python_Database_Version_Control
Author: Ken Ho
Author-email: kenho811@gmail.com
License: Apache License 2.0
Project-URL: Documentation, https://python-database-version-control.readthedocs.io/en/latest/
Project-URL: Source Code, https://github.com/kenho811/Python_Database_Version_Control
Project-URL: PyPI, https://pypi.org/project/database-version-control/
Project-URL: Docker Code, https://hub.docker.com/repository/docker/kenho811/database-version-control#
Project-URL: YouTube, https://www.youtube.com/watch?v=9l3m7zBxN4Y
Platform: UNKNOWN
Classifier: Programming Language :: Python :: 3
Requires-Python: >=3.7.*
Provides-Extra: dev
License-File: LICENSE
